gesture/__init__.py
gesture/config.py
gesture/version.py
gesture-0.0.1.dist-info/LICENSE
gesture-0.0.1.dist-info/METADATA
gesture-0.0.1.dist-info/WHEEL
gesture-0.0.1.dist-info/top_level.txt
gesture-0.0.1.dist-info/RECORD
