Metadata-Version: 2.1
Name: gesture
Version: 0.0.1
Summary: Robust Background Processing
Home-page: https://github.com/orklann/gesture
Author: Aaron Elkins
Author-email: threcius@yahoo.com
License: GPLv2.0
Platform: any
License-File: LICENSE
